sockslib/__init__.py
sockslib/socks.py
sockslib/socksauth.py
sockslib-1.7.6.dist-info/LICENSE
sockslib-1.7.6.dist-info/METADATA
sockslib-1.7.6.dist-info/WHEEL
sockslib-1.7.6.dist-info/top_level.txt
sockslib-1.7.6.dist-info/RECORD
