Metadata-Version: 2.1
Name: sockslib
Version: 1.7.6
Summary: Simple Socks proxy library
Home-page: https://github.com/woo200/sockslib
Author: Jack Woo
Author-email: woo.jack.06@gmail.com
License: MIT
Classifier: License :: OSI Approved :: MIT License
Classifier: Programming Language :: Python :: 3
Classifier: Programming Language :: Python :: 3.9
License-File: LICENSE
